{
  "lastUpdated": "2026-05-15T21:28:07.073Z",
  "totalPicks": 15,
  "stocks": [
    {
      "symbol": "AMZN",
      "name": "Amazon.com, Inc.",
      "price": 264.14,
      "change": 0,
      "changePercent": 0,
      "rating": "STRONG BUY",
      "timeframe": "1m",
      "algorithm": "Volatility-Adjusted Momentum (V2)",
      "score": 100,
      "risk": "Low",
      "stopLoss": 250.93,
      "indicators": {
        "ulcerIndex": 2.946931644358642,
        "totalReturn": 25.715101248248967,
        "martinRatio": 8.723099566253204
      },
      "allAlgorithms": [
        "Volatility-Adjusted Momentum (V2)"
      ],
      "slippageSimulated": true,
      "entryPrice": 264.14,
      "simulatedEntryPrice": 265.4607,
      "pickedAt": "2026-05-15T21:28:07.073Z",
      "pickHash": "7aa5ab94567f327a4b787f1440473cee9cc43e93264cf3d75f547d7b92169b8b"
    },
    {
      "symbol": "AMD",
      "name": "Advanced Micro Devices, Inc.",
      "price": 424.1,
      "change": 0,
      "changePercent": 0,
      "rating": "STRONG BUY",
      "timeframe": "1m",
      "algorithm": "Volatility-Adjusted Momentum (V2)",
      "score": 100,
      "risk": "Low",
      "stopLoss": 402.89,
      "indicators": {
        "ulcerIndex": 4.854882494000122,
        "totalReturn": 111.89108815029014,
        "martinRatio": 23.042379688664546
      },
      "allAlgorithms": [
        "Volatility-Adjusted Momentum (V2)"
      ],
      "slippageSimulated": true,
      "entryPrice": 424.1,
      "simulatedEntryPrice": 426.2205,
      "pickedAt": "2026-05-15T21:28:07.073Z",
      "pickHash": "326ed60ff31b283f67e2542ef317c15ffb810ae775f5940c7f4fc5d7d6d39785"
    },
    {
      "symbol": "UNH",
      "name": "UnitedHealth Group Incorporated",
      "price": 393.85,
      "change": 0,
      "changePercent": 0,
      "rating": "STRONG BUY",
      "timeframe": "1m",
      "algorithm": "Volatility-Adjusted Momentum (V2)",
      "score": 100,
      "risk": "Low",
      "stopLoss": 374.16,
      "indicators": {
        "ulcerIndex": 4.076568132087456,
        "totalReturn": 35.81034482758621,
        "martinRatio": 8.782279944211156
      },
      "allAlgorithms": [
        "Volatility-Adjusted Momentum (V2)"
      ],
      "slippageSimulated": true,
      "entryPrice": 393.85,
      "simulatedEntryPrice": 395.8192,
      "pickedAt": "2026-05-15T21:28:07.073Z",
      "pickHash": "83c8cbf4418aa34dd2555070582a5a6df5163c01ff43f33f5a3e397619ab4de2"
    },
    {
      "symbol": "GOOGL",
      "name": "Alphabet Inc.",
      "price": 396.78,
      "change": 0,
      "changePercent": 0,
      "rating": "STRONG BUY",
      "timeframe": "1m",
      "algorithm": "Volatility-Adjusted Momentum (V2)",
      "score": 91,
      "risk": "Low",
      "stopLoss": 376.94,
      "indicators": {
        "ulcerIndex": 4.048469558797399,
        "totalReturn": 25.969898457214295,
        "martinRatio": 6.413160558472445
      },
      "allAlgorithms": [
        "Volatility-Adjusted Momentum (V2)"
      ],
      "slippageSimulated": true,
      "entryPrice": 396.78,
      "simulatedEntryPrice": 398.7639,
      "pickedAt": "2026-05-15T21:28:07.073Z",
      "pickHash": "2e288fa502f38aff0ab7c3d8cb4d816de797dfdcf2f28c443f4f12609fe1e9b9"
    },
    {
      "symbol": "UNH",
      "name": "UnitedHealth Group Incorporated",
      "price": 393.85,
      "change": 0,
      "changePercent": 0,
      "rating": "STRONG BUY",
      "timeframe": "1m",
      "algorithm": "Adversarial Trend (V2)",
      "score": 87,
      "risk": "Medium",
      "stopLoss": 374.16,
      "indicators": {
        "trendStrength": 0.2297098650923994,
        "avgVolatilty": 0.014524086837398115
      },
      "allAlgorithms": [
        "Adversarial Trend (V2)"
      ],
      "slippageSimulated": true,
      "entryPrice": 393.85,
      "simulatedEntryPrice": 395.8192,
      "pickedAt": "2026-05-15T21:28:07.073Z",
      "pickHash": "e83ffec4cf953229351462aa696298919662fb66560a356c52d1bc8f72ea3408"
    },
    {
      "symbol": "AVGO",
      "name": "Broadcom Inc.",
      "price": 425.19,
      "change": 0,
      "changePercent": 0,
      "rating": "BUY",
      "timeframe": "1m",
      "algorithm": "Volatility-Adjusted Momentum (V2)",
      "score": 85,
      "risk": "Low",
      "stopLoss": 403.93,
      "indicators": {
        "ulcerIndex": 5.203480687436947,
        "totalReturn": 27.819031354713523,
        "martinRatio": 5.345207913224781
      },
      "allAlgorithms": [
        "Volatility-Adjusted Momentum (V2)"
      ],
      "slippageSimulated": true,
      "entryPrice": 425.19,
      "simulatedEntryPrice": 427.3159,
      "pickedAt": "2026-05-15T21:28:07.073Z",
      "pickHash": "f4a0638930bc907acef381b623d1096aa40cc3565a5ba737614e1c2f7e69b552"
    },
    {
      "symbol": "AMD",
      "name": "Advanced Micro Devices, Inc.",
      "price": 424.1,
      "change": 0,
      "changePercent": 0,
      "rating": "BUY",
      "timeframe": "1m",
      "algorithm": "Adversarial Trend (V2)",
      "score": 84,
      "risk": "Medium",
      "stopLoss": 402.89,
      "indicators": {
        "trendStrength": 0.5189142571810759,
        "avgVolatilty": 0.04850766508298575
      },
      "allAlgorithms": [
        "Adversarial Trend (V2)"
      ],
      "slippageSimulated": true,
      "entryPrice": 424.1,
      "simulatedEntryPrice": 426.2205,
      "pickedAt": "2026-05-15T21:28:07.073Z",
      "pickHash": "6764e7ad98c549d2a3e50be99dd7ed10b8e1482ca10dcb702b3587fb8c696957"
    },
    {
      "symbol": "GOOGL",
      "name": "Alphabet Inc.",
      "price": 396.78,
      "change": 0,
      "changePercent": 0,
      "rating": "BUY",
      "timeframe": "1m",
      "algorithm": "Adversarial Trend (V2)",
      "score": 77,
      "risk": "Medium",
      "stopLoss": 376.94,
      "indicators": {
        "trendStrength": 0.1924597179667481,
        "avgVolatilty": 0.01634912081155489
      },
      "allAlgorithms": [
        "Adversarial Trend (V2)"
      ],
      "slippageSimulated": true,
      "entryPrice": 396.78,
      "simulatedEntryPrice": 398.7639,
      "pickedAt": "2026-05-15T21:28:07.073Z",
      "pickHash": "70151e0e1bfb9d669338c0625c7c0c26f4b3be23f045dc573a1dfd67949c5ce6"
    },
    {
      "symbol": "MSTR",
      "name": "Strategy Inc",
      "price": 177.42,
      "change": 0,
      "changePercent": 0,
      "rating": "BUY",
      "timeframe": "1m",
      "algorithm": "Volatility-Adjusted Momentum (V2)",
      "score": 77,
      "risk": "Low",
      "stopLoss": 168.55,
      "indicators": {
        "ulcerIndex": 8.683492425578182,
        "totalReturn": 35.38343828189648,
        "martinRatio": 4.0743242722721105
      },
      "allAlgorithms": [
        "Volatility-Adjusted Momentum (V2)"
      ],
      "slippageSimulated": true,
      "entryPrice": 177.42,
      "simulatedEntryPrice": 178.3071,
      "pickedAt": "2026-05-15T21:28:07.073Z",
      "pickHash": "b4def8847404a0b811fb73d757c6e6820be89eb33c6e711d140ad02eba6a8031"
    },
    {
      "symbol": "AFRM",
      "name": "Affirm Holdings, Inc.",
      "price": 65.82,
      "change": 0,
      "changePercent": 0,
      "rating": "BUY",
      "timeframe": "1m",
      "algorithm": "Volatility-Adjusted Momentum (V2)",
      "score": 71,
      "risk": "Low",
      "stopLoss": 62.53,
      "indicators": {
        "ulcerIndex": 8.240837424179798,
        "totalReturn": 28.83147348486742,
        "martinRatio": 3.4981851741314394
      },
      "allAlgorithms": [
        "Volatility-Adjusted Momentum (V2)"
      ],
      "slippageSimulated": true,
      "entryPrice": 65.82,
      "simulatedEntryPrice": 66.1491,
      "pickedAt": "2026-05-15T21:28:07.073Z",
      "pickHash": "18df59a8b53f9f0286d67794063d09bb345bb94c32f62d85fabc3b168fcd9ee2"
    },
    {
      "symbol": "AAPL",
      "name": "Apple Inc.",
      "price": 300.23,
      "change": 0,
      "changePercent": 0,
      "rating": "BUY",
      "timeframe": "1m",
      "algorithm": "Adversarial Trend (V2)",
      "score": 69,
      "risk": "Medium",
      "stopLoss": 285.22,
      "indicators": {
        "trendStrength": 0.12788197598233822,
        "avgVolatilty": 0.011880801269368167
      },
      "allAlgorithms": [
        "Adversarial Trend (V2)"
      ],
      "slippageSimulated": true,
      "entryPrice": 300.23,
      "simulatedEntryPrice": 301.7312,
      "pickedAt": "2026-05-15T21:28:07.073Z",
      "pickHash": "f1786b7da490a4e2cc81c7f84cd10ab0b02404d9e53d460bbc927871ca78e9aa"
    },
    {
      "symbol": "NVDA",
      "name": "NVIDIA Corporation",
      "price": 225.32,
      "change": 0,
      "changePercent": 0,
      "rating": "BUY",
      "timeframe": "1m",
      "algorithm": "Adversarial Trend (V2)",
      "score": 66,
      "risk": "Medium",
      "stopLoss": 214.05,
      "indicators": {
        "trendStrength": 0.16703060869246117,
        "avgVolatilty": 0.022451204591742067
      },
      "allAlgorithms": [
        "Adversarial Trend (V2)"
      ],
      "slippageSimulated": true,
      "entryPrice": 225.32,
      "simulatedEntryPrice": 226.4466,
      "pickedAt": "2026-05-15T21:28:07.073Z",
      "pickHash": "e5bf8f10e1f636f98c357031c81dfadd04c82572b7ddc5c5041a1f7fbef1d72c"
    },
    {
      "symbol": "CAT",
      "name": "Caterpillar Inc.",
      "price": 888.31,
      "change": 0,
      "changePercent": 0,
      "rating": "BUY",
      "timeframe": "1m",
      "algorithm": "Volatility-Adjusted Momentum (V2)",
      "score": 66,
      "risk": "Low",
      "stopLoss": 843.89,
      "indicators": {
        "ulcerIndex": 5.596999188006099,
        "totalReturn": 16.922896177409577,
        "martinRatio": 3.023025836385873
      },
      "allAlgorithms": [
        "Volatility-Adjusted Momentum (V2)"
      ],
      "slippageSimulated": true,
      "entryPrice": 888.31,
      "simulatedEntryPrice": 892.7515,
      "pickedAt": "2026-05-15T21:28:07.073Z",
      "pickHash": "d8cf685ce32f69214ae738039249c1f760dec5b3cc7250259aaf2c2257ddd969"
    },
    {
      "symbol": "NVDA",
      "name": "NVIDIA Corporation",
      "price": 225.32,
      "change": 0,
      "changePercent": 0,
      "rating": "BUY",
      "timeframe": "1m",
      "algorithm": "Volatility-Adjusted Momentum (V2)",
      "score": 64,
      "risk": "Low",
      "stopLoss": 214.05,
      "indicators": {
        "ulcerIndex": 6.781837152837857,
        "totalReturn": 18.701923562328233,
        "martinRatio": 2.757242012585187
      },
      "allAlgorithms": [
        "Volatility-Adjusted Momentum (V2)"
      ],
      "slippageSimulated": true,
      "entryPrice": 225.32,
      "simulatedEntryPrice": 226.4466,
      "pickedAt": "2026-05-15T21:28:07.073Z",
      "pickHash": "a4fe60caad37e2d22082f21d260ff76a550b5df3af6a60e95c20498c5e9e14f5"
    },
    {
      "symbol": "AAPL",
      "name": "Apple Inc.",
      "price": 300.23,
      "change": 0,
      "changePercent": 0,
      "rating": "BUY",
      "timeframe": "1m",
      "algorithm": "Volatility-Adjusted Momentum (V2)",
      "score": 62,
      "risk": "Low",
      "stopLoss": 285.22,
      "indicators": {
        "ulcerIndex": 5.101465938749224,
        "totalReturn": 13.474191260493237,
        "martinRatio": 2.6407214515960464
      },
      "allAlgorithms": [
        "Volatility-Adjusted Momentum (V2)"
      ],
      "slippageSimulated": true,
      "entryPrice": 300.23,
      "simulatedEntryPrice": 301.7312,
      "pickedAt": "2026-05-15T21:28:07.073Z",
      "pickHash": "b3d6046b8cb79ff853806f2193d9441d5321ed4d02e831ece5a8937ecf569231"
    }
  ]
}